[
    {
        "client_msg_id": "7f8ea8a8-7cb7-4a32-97ab-2a0a7ccb3f7e",
        "type": "message",
        "text": "Plop joyeux",
        "user": "U0AA0KVLH",
        "ts": "1567149441.000400",
        "blocks": [
            {
                "type": "rich_text",
                "block_id": "cafdX",
                "elements": [
                    {
                        "type": "rich_text_section",
                        "elements": [
                            {
                                "type": "text",
                                "text": "Plop joyeux"
                            }
                        ]
                    }
                ]
            }
        ],
        "team": "T0A48J0MV",
        "user_team": "T0A48J0MV",
        "source_team": "T0A48J0MV",
        "user_profile": {
            "avatar_hash": "275e83af5eea",
            "image_72": "https:\/\/avatars.slack-edge.com\/2019-01-17\/526295781970_275e83af5eea190a97e5_72.png",
            "first_name": "naveed",
            "real_name": "naveed",
            "display_name": "",
            "team": "T0A48J0MV",
            "name": "naveed",
            "is_restricted": false,
            "is_ultra_restricted": false
        }
    },
    {
        "client_msg_id": "bc115dae-e85b-4d1c-b030-a4c506141f5a",
        "type": "message",
        "text": "Top!",
        "user": "U0A48EDPD",
        "ts": "1567149732.000600",
        "blocks": [
            {
                "type": "rich_text",
                "block_id": "lKTT",
                "elements": [
                    {
                        "type": "rich_text_section",
                        "elements": [
                            {
                                "type": "text",
                                "text": "Top!"
                            }
                        ]
                    }
                ]
            }
        ],
        "team": "T0A48J0MV",
        "user_team": "T0A48J0MV",
        "source_team": "T0A48J0MV",
        "user_profile": {
            "avatar_hash": "0afdabdefe98",
            "image_72": "https:\/\/avatars.slack-edge.com\/2017-05-06\/179039830384_0afdabdefe98471fc0ae_72.png",
            "first_name": "",
            "real_name": "faby",
            "display_name": "",
            "team": "T0A48J0MV",
            "name": "faby",
            "is_restricted": false,
            "is_ultra_restricted": false
        }
    },
    {
        "client_msg_id": "9fbd2d3a-b51b-4a76-816f-4ca307f0af76",
        "type": "message",
        "text": "Comment se fait-ce ?\n(Joyeux anniversaire, sinon)",
        "user": "U0A48EDPD",
        "ts": "1567149757.001200",
        "blocks": [
            {
                "type": "rich_text",
                "block_id": "QEd3",
                "elements": [
                    {
                        "type": "rich_text_section",
                        "elements": [
                            {
                                "type": "text",
                                "text": "Comment se fait-ce ?\n(Joyeux anniversaire, sinon)"
                            }
                        ]
                    }
                ]
            }
        ],
        "team": "T0A48J0MV",
        "user_team": "T0A48J0MV",
        "source_team": "T0A48J0MV",
        "user_profile": {
            "avatar_hash": "0afdabdefe98",
            "image_72": "https:\/\/avatars.slack-edge.com\/2017-05-06\/179039830384_0afdabdefe98471fc0ae_72.png",
            "first_name": "",
            "real_name": "faby",
            "display_name": "",
            "team": "T0A48J0MV",
            "name": "faby",
            "is_restricted": false,
            "is_ultra_restricted": false
        },
        "edited": {
            "user": "U0A48EDPD",
            "ts": "1567149768.000000"
        }
    },
    {
        "client_msg_id": "596827f2-7ad9-4925-ace5-d7b34f971ae9",
        "type": "message",
        "text": "je prends mon anniv' du bon côté ^^",
        "user": "U0AA0KVLH",
        "ts": "1567149784.001500",
        "blocks": [
            {
                "type": "rich_text",
                "block_id": "\/u9",
                "elements": [
                    {
                        "type": "rich_text_section",
                        "elements": [
                            {
                                "type": "text",
                                "text": "je prends mon anniv' du bon côté ^^"
                            }
                        ]
                    }
                ]
            }
        ],
        "team": "T0A48J0MV",
        "user_team": "T0A48J0MV",
        "source_team": "T0A48J0MV",
        "user_profile": {
            "avatar_hash": "275e83af5eea",
            "image_72": "https:\/\/avatars.slack-edge.com\/2019-01-17\/526295781970_275e83af5eea190a97e5_72.png",
            "first_name": "naveed",
            "real_name": "naveed",
            "display_name": "",
            "team": "T0A48J0MV",
            "name": "naveed",
            "is_restricted": false,
            "is_ultra_restricted": false
        }
    },
    {
        "client_msg_id": "7ff44725-1e04-4d5b-8c51-9f195b0c1d34",
        "type": "message",
        "text": "objectif du jour : en faire le moins possible",
        "user": "U0AA0KVLH",
        "ts": "1567150358.001800",
        "blocks": [
            {
                "type": "rich_text",
                "block_id": "C=ZP",
                "elements": [
                    {
                        "type": "rich_text_section",
                        "elements": [
                            {
                                "type": "text",
                                "text": "objectif du jour : en faire le moins possible"
                            }
                        ]
                    }
                ]
            }
        ],
        "team": "T0A48J0MV",
        "user_team": "T0A48J0MV",
        "source_team": "T0A48J0MV",
        "user_profile": {
            "avatar_hash": "275e83af5eea",
            "image_72": "https:\/\/avatars.slack-edge.com\/2019-01-17\/526295781970_275e83af5eea190a97e5_72.png",
            "first_name": "naveed",
            "real_name": "naveed",
            "display_name": "",
            "team": "T0A48J0MV",
            "name": "naveed",
            "is_restricted": false,
            "is_ultra_restricted": false
        }
    },
    {
        "client_msg_id": "25fba3ee-d477-4f6a-bd99-3c881ba7b855",
        "type": "message",
        "text": "Plop",
        "user": "U0M8SF5CG",
        "ts": "1567151066.002000",
        "blocks": [
            {
                "type": "rich_text",
                "block_id": "p=jU6",
                "elements": [
                    {
                        "type": "rich_text_section",
                        "elements": [
                            {
                                "type": "text",
                                "text": "Plop"
                            }
                        ]
                    }
                ]
            }
        ],
        "team": "T0A48J0MV",
        "user_team": "T0A48J0MV",
        "source_team": "T0A48J0MV",
        "user_profile": {
            "avatar_hash": "g0c9d4255841",
            "image_72": "https:\/\/secure.gravatar.com\/avatar\/c0c9d4255841bbe9144f72d426469028.jpg?s=72&d=https%3A%2F%2Fa.slack-edge.com%2Fdf10d%2Fimg%2Favatars%2Fava_0021-72.png",
            "first_name": "",
            "real_name": "clement.s",
            "display_name": "",
            "team": "T0A48J0MV",
            "name": "clement.s",
            "is_restricted": false,
            "is_ultra_restricted": false
        }
    },
    {
        "client_msg_id": "b505deba-8bcb-47d8-b4c9-1260432a52c5",
        "type": "message",
        "text": "Bon anniversaire",
        "user": "U0M8SF5CG",
        "ts": "1567151082.002200",
        "blocks": [
            {
                "type": "rich_text",
                "block_id": "\/v=W4",
                "elements": [
                    {
                        "type": "rich_text_section",
                        "elements": [
                            {
                                "type": "text",
                                "text": "Bon anniversaire"
                            }
                        ]
                    }
                ]
            }
        ],
        "team": "T0A48J0MV",
        "user_team": "T0A48J0MV",
        "source_team": "T0A48J0MV",
        "user_profile": {
            "avatar_hash": "g0c9d4255841",
            "image_72": "https:\/\/secure.gravatar.com\/avatar\/c0c9d4255841bbe9144f72d426469028.jpg?s=72&d=https%3A%2F%2Fa.slack-edge.com%2Fdf10d%2Fimg%2Favatars%2Fava_0021-72.png",
            "first_name": "",
            "real_name": "clement.s",
            "display_name": "",
            "team": "T0A48J0MV",
            "name": "clement.s",
            "is_restricted": false,
            "is_ultra_restricted": false
        }
    },
    {
        "client_msg_id": "00521378-98ed-4f09-a759-b5e26b292d00",
        "type": "message",
        "text": "merci !",
        "user": "U0AA0KVLH",
        "ts": "1567151087.002400",
        "blocks": [
            {
                "type": "rich_text",
                "block_id": "nPD8a",
                "elements": [
                    {
                        "type": "rich_text_section",
                        "elements": [
                            {
                                "type": "text",
                                "text": "merci !"
                            }
                        ]
                    }
                ]
            }
        ],
        "team": "T0A48J0MV",
        "user_team": "T0A48J0MV",
        "source_team": "T0A48J0MV",
        "user_profile": {
            "avatar_hash": "275e83af5eea",
            "image_72": "https:\/\/avatars.slack-edge.com\/2019-01-17\/526295781970_275e83af5eea190a97e5_72.png",
            "first_name": "naveed",
            "real_name": "naveed",
            "display_name": "",
            "team": "T0A48J0MV",
            "name": "naveed",
            "is_restricted": false,
            "is_ultra_restricted": false
        }
    }
]